[{"word":"Pronto!","start":0,"end":0.592},{"word":"Você","start":1.033,"end":1.254},{"word":"já","start":1.3,"end":1.37},{"word":"tem","start":1.416,"end":1.533},{"word":"uma","start":1.556,"end":1.649},{"word":"visão","start":1.683,"end":1.939},{"word":"geral","start":1.985,"end":2.287},{"word":"do","start":2.345,"end":2.403},{"word":"módulo.","start":2.45,"end":2.891},{"word":"Agora","start":3.065,"end":3.634},{"word":"é","start":3.727,"end":3.808},{"word":"hora","start":3.866,"end":4.04},{"word":"de","start":4.075,"end":4.133},{"word":"praticar.","start":4.168,"end":4.807},{"word":"Vai","start":5.132,"end":5.306},{"word":"com","start":5.341,"end":5.445},{"word":"calma,","start":5.503,"end":6.002},{"word":"leia","start":6.211,"end":6.548},{"word":"cada","start":6.618,"end":6.931},{"word":"exercício","start":6.954,"end":7.488},{"word":"com","start":7.535,"end":7.628},{"word":"atenção,","start":7.674,"end":8.313},{"word":"e","start":8.464,"end":8.58},{"word":"confie","start":8.638,"end":9.067},{"word":"no","start":9.091,"end":9.16},{"word":"processo.","start":9.195,"end":9.868},{"word":"Você","start":10.252,"end":10.832},{"word":"consegue!","start":11.041,"end":12.446}]